outflow/__init__.py
outflow/__main__.py
outflow/core/__init__.py
outflow/core/backends/__init__.py
outflow/core/backends/default.py
outflow/core/backends/parallel.py
outflow/core/block.py
outflow/core/commands/__init__.py
outflow/core/commands/argument.py
outflow/core/commands/command.py
outflow/core/commands/root_command.py
outflow/core/db/__init__.py
outflow/core/db/alembic/__init__.py
outflow/core/db/alembic/env.py
outflow/core/db/alembic/helpers.py
outflow/core/db/alembic/operations.py
outflow/core/db/alembic/script.py.mako
outflow/core/db/database.py
outflow/core/db/declarative_base_model.py
outflow/core/db/handlers.py
outflow/core/db/non_null_column.py
outflow/core/db/skip_if_untracked.py
outflow/core/exceptions/__init__.py
outflow/core/exceptions/exit_pipeline.py
outflow/core/exceptions/iochecker.py
outflow/core/exceptions/tasks.py
outflow/core/generic/__init__.py
outflow/core/generic/cached_dict.py
outflow/core/generic/constants.py
outflow/core/generic/context_manager/__init__.py
outflow/core/generic/context_manager/context_manager.py
outflow/core/generic/context_manager/managed_class.py
outflow/core/generic/context_manager/read_write_context_manager.py
outflow/core/generic/ignore_unexpected_kwargs.py
outflow/core/generic/lazy_import.py
outflow/core/generic/lazy_object_proxy.py
outflow/core/generic/metaclasses.py
outflow/core/generic/null_object.py
outflow/core/generic/serializable_proxy.py
outflow/core/generic/shell.py
outflow/core/generic/string.py
outflow/core/logging/__init__.py
outflow/core/logging/config.json
outflow/core/logging/formatter.py
outflow/core/logging/logger.py
outflow/core/logging/rotating_file_handler.py
outflow/core/logging/socket_receiver.py
outflow/core/logging/stream_handler.py
outflow/core/pipeline/__init__.py
outflow/core/pipeline/context_manager.py
outflow/core/pipeline/default_settings.py
outflow/core/pipeline/lazy_config.py
outflow/core/pipeline/lazy_context.py
outflow/core/pipeline/lazy_settings.py
outflow-0.9.2.dist-info/LICENCE
outflow-0.9.2.dist-info/LICENSE
outflow-0.9.2.dist-info/METADATA
outflow-0.9.2.dist-info/WHEEL
outflow-0.9.2.dist-info/RECORD
