Metadata-Version: 2.3
Name: outflow
Version: 0.9.2
Summary: Outflow is a framework that helps you create and execute sequential, parallel as well as distributed task workflows.
License: CECILL-2.1
Keywords: outflow,pipeline,distributed,parallel,workflow,data science,slurm
Author: Gregoire Duvauchelle
Author-email: gregoire.duvauchelle@lam.fr
Requires-Python: >=3.9,<4
Classifier: Development Status :: 4 - Beta
Classifier: Environment :: Console
Classifier: License :: OSI Approved :: CEA CNRS Inria Logiciel Libre License, version 2.1 (CeCILL-2.1)
Classifier: Programming Language :: Python :: 3
Classifier: Programming Language :: Python :: 3.9
Classifier: Programming Language :: Python :: 3.10
Classifier: Programming Language :: Python :: 3.11
Classifier: Programming Language :: Python :: 3.12
Classifier: Programming Language :: Python :: 3.13
Classifier: Programming Language :: Python :: 3 :: Only
Classifier: Topic :: Software Development :: Libraries :: Application Frameworks
Classifier: Topic :: Software Development :: Libraries :: Python Modules
Provides-Extra: ipython
Provides-Extra: tests
Requires-Dist: alembic (>=1.16,<1.17)
Requires-Dist: black (>=25.1.0,<25.2.0)
Requires-Dist: cloudpickle (>=3.1.1,<4.0.0)
Requires-Dist: declic (>=1.0.2)
Requires-Dist: importlib-metadata (>=4.8.1,<4.9.0) ; python_version < "3.8"
Requires-Dist: ipython (>=8.4.0,<9.0.0) ; extra == "tests" or extra == "ipython"
Requires-Dist: jinja2 (>=3.1.2,<4.0.0)
Requires-Dist: networkx (>2.6)
Requires-Dist: psycopg2-binary (>=2.9.1,<2.10.0)
Requires-Dist: pytest (>=8.4,<9.0) ; extra == "tests"
Requires-Dist: pytest-cov (>=6.2,<7.0) ; extra == "tests"
Requires-Dist: pytest-postgresql (>=7.0,<8.0) ; extra == "tests"
Requires-Dist: pytest-timeout (>=2.4,<3.0) ; extra == "tests"
Requires-Dist: pyyaml (>=6,<7)
Requires-Dist: pyyaml-include (>=2.0,<3.0)
Requires-Dist: rich (>10.13.0)
Requires-Dist: simple-slurm (>=0.2.2,<0.3.0)
Requires-Dist: sqlalchemy (<2)
Requires-Dist: toml (>=0.10.1,<0.11.0)
Requires-Dist: typeguard (>=4.4.4,<4.5.0)
Requires-Dist: typing-extensions (>3.10.0.2)
Project-URL: Documentation, https://docs.outflow.dev
Project-URL: Homepage, https://outflow.dev
Project-URL: Repository, https://gitlab.com/outflow-project/outflow
Project-URL: Tracker, https://gitlab.com/outflow-project/outflow/-/issues
